autonomi/client/__init__.py
autonomi/client/_client.py
autonomi/client/_connection.py
autonomi/client/_frameserver.py
autonomi/client/_jobs.py
autonomi/client/_render.py
autonomi/client/_render_utils.py
autonomi/client/_search.py
autonomi/client/_store.py
autonomi/client/_version.py
autonomi/client/constants.py
autonomi/client/exceptions.py
autonomi/client/utils.py
autonomi/client/cli/__init__.py
autonomi/client/cli/cli.py
autonomi-0.1.5.dist-info/LICENSE
autonomi-0.1.5.dist-info/METADATA
autonomi-0.1.5.dist-info/WHEEL
autonomi-0.1.5.dist-info/entry_points.txt
autonomi-0.1.5.dist-info/top_level.txt
autonomi-0.1.5.dist-info/RECORD
