Metadata-Version: 2.1
Name: autonomi
Version: 0.1.5
Summary: Autonomi Cloud Python Client
Home-page: https://www.autonomi.ai
Download-URL: https://github.com/autonomi-ai/autonomi-client
Author: Sudeep Pillai
Author-email: sudeep@autonomi.ai
License: MIT License        
Project-URL: Documentation, https://docs.autonomi.ai
Project-URL: Source Code, https://github.com/autonomi-ai/autonomi-client
Classifier: Development Status :: 3 - Alpha
Classifier: Programming Language :: Python
Classifier: Topic :: Software Development :: Libraries
Classifier: Topic :: Scientific/Engineering :: Artificial Intelligence
Classifier: Topic :: Scientific/Engineering :: Image Processing
Classifier: License :: OSI Approved :: MIT License
Classifier: Programming Language :: Python :: 3
Classifier: Programming Language :: Python :: 3.7
Classifier: Programming Language :: Python :: 3.8
Classifier: Programming Language :: Python :: 3.9
Requires-Python: >=3.7.3
License-File: LICENSE
Requires-Dist: click (>=8.1.0)
Requires-Dist: cloudpathlib[gs,s3]
Requires-Dist: ipython
Requires-Dist: loguru
Requires-Dist: opencv-python-headless (>=4.6)
Requires-Dist: pandas
Requires-Dist: Pillow (==9.2.0)
Requires-Dist: pydantic[dotenv]
Requires-Dist: requests
Requires-Dist: rich (>=12.0.0)
Requires-Dist: sentry-sdk
Requires-Dist: tenacity
Requires-Dist: tqdm
Requires-Dist: typer (>=0.6.1)
Provides-Extra: all
Requires-Dist: loguru ; extra == 'all'
Requires-Dist: notebook ; extra == 'all'
Requires-Dist: opencv-python-headless (>=4.6) ; extra == 'all'
Requires-Dist: pandas ; extra == 'all'
Requires-Dist: Pillow (==9.2.0) ; extra == 'all'
Requires-Dist: pre-commit ; extra == 'all'
Requires-Dist: pytest ; extra == 'all'
Requires-Dist: pytest-cov ; extra == 'all'
Requires-Dist: pytest-dependency ; extra == 'all'
Requires-Dist: tenacity ; extra == 'all'
Provides-Extra: dev
Requires-Dist: loguru ; extra == 'dev'
Requires-Dist: notebook ; extra == 'dev'
Requires-Dist: opencv-python-headless (>=4.6) ; extra == 'dev'
Requires-Dist: pandas ; extra == 'dev'
Requires-Dist: Pillow (==9.2.0) ; extra == 'dev'
Requires-Dist: pre-commit ; extra == 'dev'
Requires-Dist: pytest ; extra == 'dev'
Requires-Dist: pytest-cov ; extra == 'dev'
Requires-Dist: pytest-dependency ; extra == 'dev'
Requires-Dist: tenacity ; extra == 'dev'
